{
  "project_info": {
    "project_number": "183393701759",
    "firebase_url": "https://craigslist-1b4f0.firebaseio.com",
    "project_id": "craigslist-1b4f0",
    "storage_bucket": "craigslist-1b4f0.appspot.com"
  },
  "client": [
    {
      "client_info": {
        "mobilesdk_app_id": "1:183393701759:android:b63afce815ae9e5c",
        "android_client_info": {
          "package_name": "edu.uml.cmunroe.craigslist"
        }
      },
      "oauth_client": [
        {
          "client_id": "183393701759-raqdnemlucn7n4mugm6v4aete2vr234p.apps.googleusercontent.com",
          "client_type": 1,
          "android_info": {
            "package_name": "edu.uml.cmunroe.craigslist",
            "certificate_hash": "3a93cc144aa20f22465d39651a1696f4bed05222"
          }
        },
        {
          "client_id": "183393701759-lodl5h9dqlm97848g5gin6nbu4ekvhkb.apps.googleusercontent.com",
          "client_type": 3
        }
      ],
      "api_key": [
        {
          "current_key": "AIzaSyDT1f3Lcso48POlaaECamcCWYJyEG8D3o8"
        }
      ],
      "services": {
        "analytics_service": {
          "status": 1
        },
        "appinvite_service": {
          "status": 2,
          "other_platform_oauth_client": [
            {
              "client_id": "183393701759-lodl5h9dqlm97848g5gin6nbu4ekvhkb.apps.googleusercontent.com",
              "client_type": 3
            }
          ]
        },
        "ads_service": {
          "status": 2
        }
      }
    }
  ],
  "configuration_version": "1"
}